{
  "title": "サンプル家系図",
  "description": "家系図アプリケーションのデモデータ",
  "persons": {
    "p1": {
      "id": "p1",
      "name": "山田 太郎",
      "gender": "M",
      "birth_date": "1950-05-15",
      "death_date": null,
      "father_id": null,
      "mother_id": null,
      "spouse_ids": ["p2"],
      "children_ids": ["p3", "p4"],
      "birth_order": null,
      "note": "家系図のルートとなる人物"
    },
    "p2": {
      "id": "p2",
      "name": "山田 花子",
      "gender": "F",
      "birth_date": "1952-10-20",
      "death_date": null,
      "father_id": null,
      "mother_id": null,
      "spouse_ids": ["p1"],
      "children_ids": ["p3", "p4"],
      "birth_order": null,
      "note": null
    },
    "p3": {
      "id": "p3",
      "name": "山田 一郎",
      "gender": "M",
      "birth_date": "1975-03-10",
      "death_date": null,
      "father_id": "p1",
      "mother_id": "p2",
      "spouse_ids": ["p5"],
      "children_ids": ["p7", "p8"],
      "birth_order": 0,
      "note": null
    },
    "p4": {
      "id": "p4",
      "name": "山田 次郎",
      "gender": "M",
      "birth_date": "1978-08-25",
      "death_date": null,
      "father_id": "p1",
      "mother_id": "p2",
      "spouse_ids": ["p6"],
      "children_ids": ["p9"],
      "birth_order": 1,
      "note": null
    },
    "p5": {
      "id": "p5",
      "name": "山田 美智子",
      "gender": "F",
      "birth_date": "1977-12-05",
      "death_date": null,
      "father_id": null,
      "mother_id": null,
      "spouse_ids": ["p3"],
      "children_ids": ["p7", "p8"],
      "birth_order": null,
      "note": null
    },
    "p6": {
      "id": "p6",
      "name": "山田 恵子",
      "gender": "F",
      "birth_date": "1980-01-30",
      "death_date": null,
      "father_id": null,
      "mother_id": null,
      "spouse_ids": ["p4"],
      "children_ids": ["p9"],
      "birth_order": null,
      "note": null
    },
    "p7": {
      "id": "p7",
      "name": "山田 健太",
      "gender": "M",
      "birth_date": "2000-06-15",
      "death_date": null,
      "father_id": "p3",
      "mother_id": "p5",
      "spouse_ids": [],
      "children_ids": [],
      "birth_order": 0,
      "note": null
    },
    "p8": {
      "id": "p8",
      "name": "山田 裕子",
      "gender": "F",
      "birth_date": "2003-09-20",
      "death_date": null,
      "father_id": "p3",
      "mother_id": "p5",
      "spouse_ids": [],
      "children_ids": [],
      "birth_order": 1,
      "note": null
    },
    "p9": {
      "id": "p9",
      "name": "山田 真一",
      "gender": "M",
      "birth_date": "2005-04-10",
      "death_date": null,
      "father_id": "p4",
      "mother_id": "p6",
      "spouse_ids": [],
      "children_ids": [],
      "birth_order": 0,
      "note": null
    }
  }
}
